Metadata-Version: 2.1
Name: algepy
Version: 0.0.3
Summary: Algebra and Analytic Geometry in Python
Home-page: https://github.com/manucabral/algepy
Author: Manuel Cabral
Author-email: cabral.manuel@yandex.com
License: GPLv3
Keywords: python,algebra,math,geometry,vector,algepy
Platform: UNKNOWN
Classifier: Intended Audience :: Developers
Classifier: Topic :: Software Development :: Build Tools
Classifier: Programming Language :: Python :: 3
Classifier: Programming Language :: Python :: 3.9
Classifier: Operating System :: Unix
Classifier: Operating System :: MacOS :: MacOS X
Classifier: Operating System :: Microsoft :: Windows
Requires-Python: >= 3.9
